sglang/__init__.py
sglang/api.py
sglang/global_config.py
sglang/launch_server.py
sglang/utils.py
sglang/backend/__init__.py
sglang/backend/anthropic.py
sglang/backend/base_backend.py
sglang/backend/openai.py
sglang/backend/runtime_endpoint.py
sglang/backend/vertexai.py
sglang/lang/__init__.py
sglang/lang/chat_template.py
sglang/lang/compiler.py
sglang/lang/interpreter.py
sglang/lang/ir.py
sglang/lang/tracer.py
sglang/srt/backend_config.py
sglang/srt/conversation.py
sglang/srt/hf_transformers_utils.py
sglang/srt/memory_pool.py
sglang/srt/mm_utils.py
sglang/srt/model_config.py
sglang/srt/sampling_params.py
sglang/srt/server.py
sglang/srt/server_args.py
sglang/srt/utils.py
sglang/srt/constrained/__init__.py
sglang/srt/constrained/base_cache.py
sglang/srt/constrained/fsm_cache.py
sglang/srt/constrained/jump_forward.py
sglang/srt/layers/context_flashattention_nopad.py
sglang/srt/layers/extend_attention.py
sglang/srt/layers/logits_processor.py
sglang/srt/layers/radix_attention.py
sglang/srt/layers/token_attention.py
sglang/srt/managers/detokenizer_manager.py
sglang/srt/managers/io_struct.py
sglang/srt/managers/openai_protocol.py
sglang/srt/managers/tokenizer_manager.py
sglang/srt/managers/router/infer_batch.py
sglang/srt/managers/router/manager.py
sglang/srt/managers/router/model_rpc.py
sglang/srt/managers/router/model_runner.py
sglang/srt/managers/router/radix_cache.py
sglang/srt/managers/router/scheduler.py
sglang/srt/models/llama2.py
sglang/srt/models/llava.py
sglang/srt/models/mistral.py
sglang/srt/models/mixtral.py
sglang/srt/models/qwen.py
sglang/srt/models/qwen2.py
sglang/srt/models/yivl.py
sglang/test/test_conversation.py
sglang/test/test_openai_protocol.py
sglang/test/test_programs.py
sglang/test/test_utils.py
mytempsgdepfix-0.1.12.dist-info/METADATA
mytempsgdepfix-0.1.12.dist-info/WHEEL
mytempsgdepfix-0.1.12.dist-info/top_level.txt
mytempsgdepfix-0.1.12.dist-info/RECORD
