Metadata-Version: 2.1
Name: mytempsgdepfix
Version: 0.1.12
Summary: A structured generation langauge for LLMs.
Project-URL: Homepage, https://github.com/sgl-project/sglang
Project-URL: Bug Tracker, https://github.com/sgl-project/sglang/issues
Classifier: Programming Language :: Python :: 3
Classifier: License :: OSI Approved :: Apache Software License
Requires-Python: >=3.8
Requires-Dist: requests
Provides-Extra: all
Requires-Dist: mytempsgdepfix[srt] ; extra == 'all'
Requires-Dist: mytempsgdepfix[openai] ; extra == 'all'
Requires-Dist: mytempsgdepfix[anthropic] ; extra == 'all'
Provides-Extra: anthropic
Requires-Dist: anthropic ; extra == 'anthropic'
Requires-Dist: numpy ; extra == 'anthropic'
Provides-Extra: openai
Requires-Dist: openai >=1.0 ; extra == 'openai'
Requires-Dist: numpy ; extra == 'openai'
Provides-Extra: srt
Requires-Dist: aiohttp ; extra == 'srt'
Requires-Dist: fastapi ; extra == 'srt'
Requires-Dist: psutil ; extra == 'srt'
Requires-Dist: rpyc ; extra == 'srt'
Requires-Dist: torch ; extra == 'srt'
Requires-Dist: uvloop ; extra == 'srt'
Requires-Dist: uvicorn ; extra == 'srt'
Requires-Dist: zmq ; extra == 'srt'
Requires-Dist: vllm ==0.3.0 ; extra == 'srt'
Requires-Dist: interegular ; extra == 'srt'
Requires-Dist: lark ; extra == 'srt'
Requires-Dist: numba ; extra == 'srt'
Requires-Dist: pydantic ; extra == 'srt'
Requires-Dist: referencing ; extra == 'srt'
Requires-Dist: diskcache ; extra == 'srt'
Requires-Dist: cloudpickle ; extra == 'srt'
Requires-Dist: pillow ; extra == 'srt'
Requires-Dist: outlines ==0.0.30 ; extra == 'srt'
